kicad_lib_manager/__init__.py
kicad_lib_manager/__main__.py
kicad_lib_manager/main.py
kicad_lib_manager/commands/__init__.py
kicad_lib_manager/commands/add_3d/.command
kicad_lib_manager/commands/add_3d/__init__.py
kicad_lib_manager/commands/add_3d/command.py
kicad_lib_manager/commands/add_3d/docs.mdx
kicad_lib_manager/commands/add_hook/.command
kicad_lib_manager/commands/add_hook/__init__.py
kicad_lib_manager/commands/add_hook/command.py
kicad_lib_manager/commands/add_hook/docs.mdx
kicad_lib_manager/commands/config/__init__.py
kicad_lib_manager/commands/config/command.py
kicad_lib_manager/commands/config/docs.mdx
kicad_lib_manager/commands/init/__init__.py
kicad_lib_manager/commands/init/command.py
kicad_lib_manager/commands/init/docs.mdx
kicad_lib_manager/commands/list_libraries/.command
kicad_lib_manager/commands/list_libraries/__init__.py
kicad_lib_manager/commands/list_libraries/command.py
kicad_lib_manager/commands/list_libraries/docs.mdx
kicad_lib_manager/commands/pin/__init__.py
kicad_lib_manager/commands/pin/command.py
kicad_lib_manager/commands/pin/docs.mdx
kicad_lib_manager/commands/setup/__init__.py
kicad_lib_manager/commands/setup/command.py
kicad_lib_manager/commands/setup/docs.mdx
kicad_lib_manager/commands/status/__init__.py
kicad_lib_manager/commands/status/command.py
kicad_lib_manager/commands/status/docs.mdx
kicad_lib_manager/commands/sync/__init__.py
kicad_lib_manager/commands/sync/command.py
kicad_lib_manager/commands/sync/docs.mdx
kicad_lib_manager/commands/template/__init__.py
kicad_lib_manager/commands/template/command.py
kicad_lib_manager/commands/template/docs.mdx
kicad_lib_manager/commands/unpin/__init__.py
kicad_lib_manager/commands/unpin/command.py
kicad_lib_manager/commands/unpin/docs.mdx
kicad_lib_manager/commands/update/__init__.py
kicad_lib_manager/commands/update/check.py
kicad_lib_manager/commands/update/command.py
kicad_lib_manager/commands/update/docs.mdx
kicad_lib_manager/commands/update/info.py
kilm-0.5.4.dist-info/METADATA
kilm-0.5.4.dist-info/WHEEL
kilm-0.5.4.dist-info/entry_points.txt
kilm-0.5.4.dist-info/licenses/LICENSE
kilm-0.5.4.dist-info/RECORD
