Metadata-Version: 2.4
Name: kilm
Version: 0.5.4
Summary: A command-line tool for managing KiCad libraries across projects and workstations
Project-URL: Homepage, https://github.com/barisgit/KiLM
Project-URL: Documentation, https://kilm.aristovnik.me
Project-URL: Repository, https://github.com/barisgit/KiLM
Project-URL: Bug Tracker, https://github.com/barisgit/KiLM/issues
Author-email: Blaž Aristovnik <blaz@paxia.co>
Maintainer-email: Blaž Aristovnik <blaz@paxia.co>
License-Expression: MIT
License-File: LICENSE
Keywords: cli,eda,electronics,kicad,library-management,pcb-design
Classifier: Development Status :: 4 - Beta
Classifier: Environment :: Console
Classifier: Framework :: Pytest
Classifier: Intended Audience :: Developers
Classifier: Intended Audience :: Science/Research
Classifier: License :: OSI Approved :: MIT License
Classifier: Natural Language :: English
Classifier: Operating System :: OS Independent
Classifier: Programming Language :: Python :: 3
Classifier: Programming Language :: Python :: 3.9
Classifier: Programming Language :: Python :: 3.10
Classifier: Programming Language :: Python :: 3.11
Classifier: Programming Language :: Python :: 3.12
Classifier: Programming Language :: Python :: 3.13
Classifier: Topic :: Scientific/Engineering :: Electronic Design Automation (EDA)
Requires-Python: >=3.9
Requires-Dist: click>=8.0
Requires-Dist: jinja2>=3.1.6
Requires-Dist: packaging>=25.0
Requires-Dist: pathlib>=1.0.1
Requires-Dist: pathspec>=0.12.1
Requires-Dist: pyyaml>=6.0
Requires-Dist: questionary>=1.10.0
Requires-Dist: requests>=2.32.4
Requires-Dist: rich>=14.0.0
Requires-Dist: typer>=0.17.4
Provides-Extra: dev
Requires-Dist: black>=22.0.0; extra == 'dev'
Requires-Dist: flake8>=4.0.0; extra == 'dev'
Requires-Dist: pre-commit>=3.5.0; extra == 'dev'
Requires-Dist: pyrefly>=0.31.0; extra == 'dev'
Requires-Dist: pytest-cov>=4.0.0; extra == 'dev'
Requires-Dist: pytest>=7.0.0; extra == 'dev'
Requires-Dist: ruff>=0.1.0; extra == 'dev'
